<?xml version="1.0" encoding="utf-8"?>
<LanguageData>
  <BrushTurkey.label>brush turkey</BrushTurkey.label>
  <BrushTurkey.labelPlural>brush turkeys</BrushTurkey.labelPlural>
  <BrushTurkey.lifeStages.0.label>brush turkey</BrushTurkey.lifeStages.0.label>
  <BrushTurkey.lifeStages.0.labelPlural>brush turkey</BrushTurkey.lifeStages.0.labelPlural>
  <BrushTurkey.lifeStages.0.labelMale>male brush turkey</BrushTurkey.lifeStages.0.labelMale>
  <BrushTurkey.lifeStages.0.labelMalePlural>male brush turkeys</BrushTurkey.lifeStages.0.labelMalePlural>
  <BrushTurkey.lifeStages.0.labelFemale>female brush turkey</BrushTurkey.lifeStages.0.labelFemale>
  <BrushTurkey.lifeStages.0.labelFemalePlural>female brush turkeys</BrushTurkey.lifeStages.0.labelFemalePlural>
  <BrushTurkey.lifeStages.1.label>brush turkey</BrushTurkey.lifeStages.1.label>
  <BrushTurkey.lifeStages.1.labelPlural>brush turkey</BrushTurkey.lifeStages.1.labelPlural>
  <BrushTurkey.lifeStages.1.labelMale>male brush turkey</BrushTurkey.lifeStages.1.labelMale>
  <BrushTurkey.lifeStages.1.labelMalePlural>male brush turkeys</BrushTurkey.lifeStages.1.labelMalePlural>
  <BrushTurkey.lifeStages.1.labelFemale>female brush turkey</BrushTurkey.lifeStages.1.labelFemale>
  <BrushTurkey.lifeStages.1.labelFemalePlural>female brush turkeys</BrushTurkey.lifeStages.1.labelFemalePlural>
  <BrushTurkey.lifeStages.2.label>brush turkey</BrushTurkey.lifeStages.2.label>
  <BrushTurkey.lifeStages.2.labelPlural>brush turkey</BrushTurkey.lifeStages.2.labelPlural>
  <BrushTurkey.lifeStages.2.labelMale>male brush turkey</BrushTurkey.lifeStages.2.labelMale>
  <BrushTurkey.lifeStages.2.labelMalePlural>male brush turkeys</BrushTurkey.lifeStages.2.labelMalePlural>
  <BrushTurkey.lifeStages.2.labelFemale>female brush turkey</BrushTurkey.lifeStages.2.labelFemale>
  <BrushTurkey.lifeStages.2.labelFemalePlural>female brush turkeys</BrushTurkey.lifeStages.2.labelFemalePlural>
  <BrushTurkey.labelMale>male brush turkey</BrushTurkey.labelMale>
  <BrushTurkey.labelMalePlural>male brush turkeys</BrushTurkey.labelMalePlural>
  <BrushTurkey.labelFemale>female brush turkey</BrushTurkey.labelFemale>
  <BrushTurkey.labelFemalePlural>female brush turkeys</BrushTurkey.labelFemalePlural>
</LanguageData>
