<?xml version="1.0" encoding="utf-8"?>
<LanguageData>
  <!--The following translations were generated by https://www.deepl.com/-->
  <!-- EN: highland cow -->
  <HighlandCow.label>vache des hauts plateaux</HighlandCow.label>
  <!-- EN: highland bull -->
  <HighlandCow.labelMale>taureau des hautes terres</HighlandCow.labelMale>
  <!-- EN: highland calf -->
  <HighlandCow.lifeStages.highland_calf.label>veau des hautes terres</HighlandCow.lifeStages.highland_calf.label>
  <!-- EN: highland calves -->
  <HighlandCow.lifeStages.highland_calf.labelPlural>veaux des hautes terres</HighlandCow.lifeStages.highland_calf.labelPlural>
</LanguageData>
